meter_lib/__init__.py
meter_lib/core.py
meter_lib-0.0.7.dist-info/METADATA
meter_lib-0.0.7.dist-info/WHEEL
meter_lib-0.0.7.dist-info/RECORD
